mongo_analyser/__init__.py
mongo_analyser/__main__.py
mongo_analyser/app.tcss
mongo_analyser/core/__init__.py
mongo_analyser/core/analyser.py
mongo_analyser/core/config_manager.py
mongo_analyser/core/db.py
mongo_analyser/core/extractor.py
mongo_analyser/core/shared.py
mongo_analyser/dialogs/__init__.py
mongo_analyser/dialogs/confirm_dialog.py
mongo_analyser/dialogs/error_dialog.py
mongo_analyser/llm_chat/__init__.py
mongo_analyser/llm_chat/base.py
mongo_analyser/llm_chat/google.py
mongo_analyser/llm_chat/interface.py
mongo_analyser/llm_chat/ollama.py
mongo_analyser/llm_chat/openai.py
mongo_analyser/llm_chat/wrapper.py
mongo_analyser/py.typed
mongo_analyser/tui.py
mongo_analyser/views/__init__.py
mongo_analyser/views/chat_view.py
mongo_analyser/views/config_view.py
mongo_analyser/views/data_explorer_view.py
mongo_analyser/views/db_connection_view.py
mongo_analyser/views/schema_analysis_view.py
mongo_analyser/widgets/__init__.py
mongo_analyser/widgets/chat_input.py
mongo_analyser/widgets/chat_message_list.py
mongo_analyser/widgets/chat_message_widget.py
mongo_analyser/widgets/collection_stats_widget.py
mongo_analyser/widgets/llm_config_panel.py
mongo_analyser-0.2.1.dist-info/LICENSE
mongo_analyser-0.2.1.dist-info/METADATA
mongo_analyser-0.2.1.dist-info/WHEEL
mongo_analyser-0.2.1.dist-info/entry_points.txt
mongo_analyser-0.2.1.dist-info/RECORD
