Metadata-Version: 2.3
Name: mongo-analyser
Version: 0.2.1
Summary: Analyze and understand data stored in MongoDB from the command line
License: MIT
Keywords: mongodb,no-sql,json,ollama,openai,llm,ai,terminal,tui
Author: Hassan Abedi
Author-email: hassan.abedi.t@gmail.com
Maintainer: Hassan Abedi
Maintainer-email: hassan.abedi.t@gmail.com
Requires-Python: >=3.10,<4.0
Classifier: License :: OSI Approved :: MIT License
Classifier: Environment :: Console
Classifier: Development Status :: 4 - Beta
Classifier: Intended Audience :: Developers
Classifier: Intended Audience :: End Users/Desktop
Classifier: Intended Audience :: Other Audience
Classifier: Programming Language :: Python :: 3
Classifier: Programming Language :: Python :: 3.11
Classifier: Programming Language :: Python :: 3.12
Classifier: Programming Language :: Python :: 3.13
Classifier: Topic :: Terminals
Classifier: Topic :: Scientific/Engineering :: Artificial Intelligence
Classifier: Typing :: Typed
Provides-Extra: dev
Requires-Dist: dnspython (>=2.7.0,<3.0.0)
Requires-Dist: google-generativeai (>=0.8.5,<0.9.0)
Requires-Dist: griffe (>=1.7.3,<2.0.0) ; extra == "dev"
Requires-Dist: icecream (>=2.1.4,<3.0.0) ; extra == "dev"
Requires-Dist: mkdocs (>=1.6.1,<2.0.0) ; extra == "dev"
Requires-Dist: mkdocs-material (>=9.6.14,<10.0.0) ; extra == "dev"
Requires-Dist: mkdocstrings-python (>=1.16.10,<2.0.0) ; extra == "dev"
Requires-Dist: mypy (>=1.11.1) ; extra == "dev"
Requires-Dist: ollama (>=0.4.8,<0.5.0)
Requires-Dist: openai (>=1.81.0,<2.0.0)
Requires-Dist: pre-commit (>=4.2.0,<5.0.0) ; extra == "dev"
Requires-Dist: pymongo (>=4.13.0,<5.0.0)
Requires-Dist: pytest (>=8.0.1) ; extra == "dev"
Requires-Dist: pytest-asyncio (>=0.26.0,<0.27.0) ; extra == "dev"
Requires-Dist: pytest-cov (>=6.0.0) ; extra == "dev"
Requires-Dist: pytest-mock (>=3.14.0) ; extra == "dev"
Requires-Dist: python-dotenv (>=1.1.0,<2.0.0)
Requires-Dist: pytz (>=2025.1,<2026.0)
Requires-Dist: ruff (>=0.9.3) ; extra == "dev"
Requires-Dist: textual (>=3.2.0,<4.0.0)
Requires-Dist: textual-dev (>=1.7.0,<2.0.0) ; extra == "dev"
Requires-Dist: types-requests (>=2.32.0.20250515,<3.0.0.0) ; extra == "dev"
Project-URL: Documentation, https://github.com/habedi/mongo-analyser/blob/main/docs/index.md
Project-URL: Repository, https://github.com/habedi/mongo-analyser
